setup.py
yapocis/__init__.py
yapocis/demo_life.py
yapocis/demo_mandelbrot.py
yapocis/demo_rpc.py
yapocis/gaussian.py
yapocis/gradient.py
yapocis/hsi.py
yapocis/median.py
yapocis/utils.py
yapocis.egg-info/PKG-INFO
yapocis.egg-info/SOURCES.txt
yapocis.egg-info/dependency_links.txt
yapocis.egg-info/not-zip-safe
yapocis.egg-info/top_level.txt
yapocis/examples/__init__.py
yapocis/examples/demo_numpy.py
yapocis/examples/demo_opencl.py
yapocis/examples/demo_yapocis.py
yapocis/examples/median3x3_comparison.py
yapocis/rpc/__init__.py
yapocis/rpc/interfacecl_parser.py
yapocis/rpc/interfaces.py
yapocis/rpc/kernels.py