Metadata-Version: 1.0
Name: yapocis
Version: 0.2.2
Summary: Yet another PyOpenCL interface specifier
Home-page: https://github.com/seantrue/Yapocis/
Author: Sean D. True
Author-email: sean.true@gmail.com
License: PSF
Keywords: opencl pyopencl thunk rpc image
Platform: UNKNOWN
Classifier: Development Status :: 3 - Alpha
Classifier: Intended Audience :: Developers
Classifier: License :: OSI Approved :: Python Software Foundation License
Classifier: Topic :: Scientific/Engineering :: Image Recognition
